openapi_fastapi_client/__init__.py
openapi_fastapi_client/api.py
openapi_fastapi_client/helpers.py
openapi_fastapi_client/main.py
openapi_fastapi_client/schema.py
openapi_fastapi_client-0.2.1.dist-info/entry_points.txt
openapi_fastapi_client-0.2.1.dist-info/WHEEL
openapi_fastapi_client-0.2.1.dist-info/METADATA
openapi_fastapi_client-0.2.1.dist-info/RECORD
