Metadata-Version: 2.1
Name: openapi-fastapi-client
Version: 0.2.1
Summary: A tool to autogenerate FastApi Clients from given openapi.yaml.
Home-page: https://github.com/FelixTheC/openapi-fastapi-client
License: MIT
Keywords: openapi,pydantic,python3
Author: FelixTheC
Author-email: felixeisenmenger@gmx.net
Requires-Python: >=3.9,<4
Classifier: License :: OSI Approved :: MIT License
Classifier: Programming Language :: Python :: 3
Classifier: Programming Language :: Python :: 3.9
Classifier: Programming Language :: Python :: 3.10
Requires-Dist: black (>=24.3.0,<25.0.0)
Requires-Dist: isort (>=6.0.1,<7.0.0)
Requires-Dist: pydantic (>=2.4.0,<3.0.0)
Requires-Dist: pyyaml (>=6.0.2,<7.0.0)
Requires-Dist: typer (>=0.15.3,<0.16.0)
Requires-Dist: typing-extensions (>=4.13.2,<5.0.0)
Project-URL: Repository, https://github.com/FelixTheC/openapi-fastapi-client
